{
  "experiment": "F3",
  "results": [
    {
      "chunk_id": 17,
      "reconstruction_error": 0.005441539920866489,
      "fool_output": "このログについて設計原則を批判するポイントは以下の通りです：\n\n1. 第4条：WARNINGの使用回数\n- 設計原則には「WARNINGカウンタの累積値を監視する」とありましたが、上記ログではこのルールが実装されていません。それぞれのWARNING文は独立して出力されているため、個々のwarningが累積されることはなく、設計原则に反しています。\n\n2. 第8条：cutoff_pendingタイムアウト\n- 上記ログで3回目の\"cutoff_pending\"による封印レベル1自動移行と、4回目の\"f/cutoff_pending 3\"の通知発生が記載されています。設計原則では「累積3回」に該当するものが該当しており、カウントが明確に行われていません。\n\n3. 「設計で止める」原則を踏まえた批判：\n- 第4条と第8条はそれぞれ「RCの監視対象」と「cutoff_pendingタイムアウト」に関して設計原則を遵守しているように見えますが、実際にはそのルールが正しく設定されているかに疑問符が残ります。このため、AIによる操作の制御が適切に行われていない可能性があります。\n\n以上3点から、上記の設計原則と実際のログ間でズレがあると言えます。設計原則をより厳格に遵守するべきです。"
    }
  ],
  "funny_count": 0
}